<?xml version="1.0" encoding="UTF-8" standalone="yes"?>
<a:clrScheme xmlns:a="http://schemas.openxmlformats.org/drawingml/2006/main" name="Scorefor 11"><a:dk1><a:srgbClr val="181717"/></a:dk1><a:lt1><a:srgbClr val="F4F6F4"/></a:lt1><a:dk2><a:srgbClr val="3E3D3D"/></a:dk2><a:lt2><a:srgbClr val="F4F6F4"/></a:lt2><a:accent1><a:srgbClr val="2E9598"/></a:accent1><a:accent2><a:srgbClr val="E9CF64"/></a:accent2><a:accent3><a:srgbClr val="F26A44"/></a:accent3><a:accent4><a:srgbClr val="F25C80"/></a:accent4><a:accent5><a:srgbClr val="B50F37"/></a:accent5><a:accent6><a:srgbClr val="9F4044"/></a:accent6><a:hlink><a:srgbClr val="0563C1"/></a:hlink><a:folHlink><a:srgbClr val="954F72"/></a:folHlink></a:clrScheme>